greapy/__init__.py
greapy/approximations.py
greapy/cli.py
greapy/cobaya.py
greapy/common.py
greapy/grea.py
greapy-0.2.0.dist-info/licenses/LICENSE
greapy-0.2.0.dist-info/METADATA
greapy-0.2.0.dist-info/WHEEL
greapy-0.2.0.dist-info/entry_points.txt
greapy-0.2.0.dist-info/top_level.txt
greapy-0.2.0.dist-info/RECORD
