Metadata-Version: 2.4
Name: greapy
Version: 0.2.0
Summary: A simple python-based implementation of the General Relativistic Entropic Acceleration (GREA) theory
Author-email: Rodrigo Calderon <calderon.cosmology@gmail.com>
License: MIT License
Project-URL: Homepage, https://github.com/rcalderonb6/greapy
Keywords: greapy
Classifier: Intended Audience :: Developers
Classifier: License :: OSI Approved :: MIT License
Classifier: Natural Language :: English
Classifier: Programming Language :: Python :: 3.8
Classifier: Programming Language :: Python :: 3.9
Classifier: Programming Language :: Python :: 3.10
Classifier: Programming Language :: Python :: 3.11
Requires-Python: >=3.8
License-File: LICENSE
Requires-Dist: numpy
Requires-Dist: scipy
Requires-Dist: typer
Provides-Extra: all
Requires-Dist: greapy[extra]; extra == "all"
Provides-Extra: extra
Requires-Dist: matplotlib; extra == "extra"
Requires-Dist: cobaya; extra == "extra"
Dynamic: license-file
